rabotaotzyvy_ru/__init__.py
rabotaotzyvy_ru/rabotaotzyvy_ru.py
rabotaotzyvy_ru-0.1.6.dist-info/LICENSE
rabotaotzyvy_ru-0.1.6.dist-info/METADATA
rabotaotzyvy_ru-0.1.6.dist-info/WHEEL
rabotaotzyvy_ru-0.1.6.dist-info/top_level.txt
rabotaotzyvy_ru-0.1.6.dist-info/RECORD
