Metadata-Version: 2.1
Name: rabotaotzyvy-ru
Version: 0.1.6
Summary: rabotaotzyvy_ru scrubber
Home-page: https://github.com/NMelis/rabotaotzyvy_ru
Author: NMelis
Author-email: melis.zhoroev@gmail.com
License: MIT license
Keywords: rabotaotzyvy_ru
Platform: UNKNOWN
Classifier: Development Status :: 2 - Pre-Alpha
Classifier: Intended Audience :: Developers
Classifier: License :: OSI Approved :: MIT License
Classifier: Natural Language :: English
Classifier: Programming Language :: Python :: 2
Classifier: Programming Language :: Python :: 2.7
Classifier: Programming Language :: Python :: 3
Classifier: Programming Language :: Python :: 3.4
Classifier: Programming Language :: Python :: 3.5
Classifier: Programming Language :: Python :: 3.6
Classifier: Programming Language :: Python :: 3.7
Requires-Dist: requests
Requires-Dist: bs4
